[{"id":1,"price":55.999,"name":"LENOVO G580","image":"https://www.notebookcheck.net/uploads/tx_nbc2/1_7be56b666dd7e709bf86626d469bf61e_03.jpg","screenSize":"15.6 in훾a","cpu":"Intel Celereon B250","screenResolution":"1920x1080 piksela","numberOfCores":" 2 jezgra","memory":"120GB HDD","ram":"4GB SATA3","visible":true},{"id":2,"price":82.799,"name":"ASUS VivoBook x512","image":"https://www.winwin.rs/media/catalog/product/865/87/8658737.jpg","screenSize":"15.6 in훾a","cpu":"AMD Ryzen 7 3600","screenResolution":"1920x1080 piksela","numberOfCores":"4","memory":"256GB SSD","ram":"4GB SATA3","visible":true},{"id":3,"price":119.999,"name":"MacBook Pro 2020","image":"https://store.storeimages.cdn-apple.com/4982/as-images.apple.com/is/mbp-spacegray-select-202011?wid\u003d892\u0026hei\u003d820\u0026\u0026qlt\u003d80\u0026.v\u003d1603406905000","screenSize":"14.5\"","cpu":"Intel i7 9834","screenResolution":"1920x1080px","numberOfCores":"4","memory":"256GB SSD","ram":"8GB SATA3","visible":true},{"id":4,"price":99.999,"name":"MacBook Air 2020","image":"https://www.bhphotovideo.com/images/images2500x2500/apple_z0x1_mvfh_05_bh_13_3_macbook_air_with_1492907.jpg","screenSize":"14.5\"","cpu":"Intel i5 5200","screenResolution":"1920x1080px","numberOfCores":"4","memory":"256GB SSD","ram":"4GB SATA3","visible":true},{"id":5,"price":45.999,"name":"ACER Aspire 5200","image":"https://www.tehnomanija.rs/UserFiles/products/142279.jpg","screenSize":"15.6 in훾a","cpu":"AMD Ryzen 3 3600","screenResolution":"1920x1080 piksela","numberOfCores":"4","memory":"256GB HDD","ram":"4GB SATA3","visible":true},{"id":6,"price":76.999,"name":"LENOVO IdeaPad 454","image":"https://www.lenovo.com/medias/lenovo-ideapad-3-15-almond-intel-hero.png?context\u003dbWFzdGVyfHJvb3R8Mjc2NTE3fGltYWdlL3BuZ3xoMWUvaDU1LzEwODU5MzUxNDc0MjA2LnBuZ3wwMWIzNGFhY2M1MTljZTNiMzAwYmE3NGFjOWFiNjU2MWIxYzI4Y2I1YmJhOTM1NDVkNmZjNjVlZWYyZGEyNmIx","screenSize":"15.6 in훾a","cpu":"AMD Ryzen 7 3600","screenResolution":"1920x1080 piksela","numberOfCores":"4","memory":"256GB SSD","ram":"8GB SATA3","visible":true}]